nonebot_plugin_ai_interviewer/__init__.py
nonebot_plugin_ai_interviewer/config.py
nonebot_plugin_ai_interviewer/interviewer.py
nonebot_plugin_ai_interviewer-0.1.1.dist-info/WHEEL
nonebot_plugin_ai_interviewer-0.1.1.dist-info/METADATA
nonebot_plugin_ai_interviewer-0.1.1.dist-info/RECORD
